[
    {
        "id": 1,
        "title": "GitHub Pages ile Ücretsiz Web Sitesi Nasıl Kurulur?",
        "date": "1 Mayıs 2026",
        "excerpt": "GitHub'ın sunduğu ücretsiz barındırma hizmeti ile statik web sitenizi dakikalar içinde nasıl yayınlayabileceğinizi öğrenin. HTML, CSS ve JS kullanarak kendi blogunuzu oluşturun.",
        "tags": [
            "GitHub",
            "Web Geliştirme",
            "Rehber"
        ],
        "hiddenTags": [
            "bedava",
            "ücretsiz site",
            "hosting",
            "yayınlama",
            "domain",
            "kodlama öğren",
            "html",
            "css",
            "javascript"
        ],
        "url": "#"
    },
    {
        "id": 2,
        "title": "Modern CSS: Glassmorphism Tasarımı",
        "date": "28 Nisan 2026",
        "excerpt": "Modern web tasarımlarının vazgeçilmezi olan cam efekti (glassmorphism) tasarımını CSS kullanarak nasıl oluşturabileceğinizi detaylıca inceliyoruz.",
        "tags": [
            "CSS",
            "Tasarım",
            "UI/UX"
        ],
        "hiddenTags": [
            "cam efekti",
            "arka plan bulanıklığı",
            "blur",
            "modern stil",
            "arayüz",
            "stil dosyası",
            "görsel"
        ],
        "url": "#"
    },
    {
        "id": 3,
        "title": "JavaScript ile Dinamik İçerik Yükleme",
        "date": "20 Nisan 2026",
        "excerpt": "Fetch API kullanarak JSON dosyalarından asenkron olarak nasıl veri çekebileceğinizi ve arayüzünüzü nasıl dinamik hale getireceğinizi anlattık.",
        "tags": [
            "JavaScript",
            "Frontend",
            "API"
        ],
        "hiddenTags": [
            "js",
            "veri çekme",
            "dinamik site",
            "json okuma",
            "backend yok",
            "asenkron",
            "fetch",
            "kod mantığı"
        ],
        "url": "#"
    },
    {
        "id": 4,
        "title": "SEO İpuçları: Blogunuzu Öne Çıkarın",
        "date": "15 Nisan 2026",
        "excerpt": "Statik blog sitenizi arama motorlarında nasıl daha üst sıralara taşıyabileceğiniz hakkında temel SEO optimizasyon teknikleri.",
        "tags": [
            "SEO",
            "İçerik",
            "Optimizasyon"
        ],
        "hiddenTags": [
            "google",
            "arama motoru",
            "üst sıralara çıkma",
            "tıklanma",
            "başarı",
            "anahtar kelime",
            "hit"
        ],
        "url": "#"
    }
]